{
  "categories": [
    {
      "slug": "conifers",
      "title": "Хвойные растения",
      "description": "Надежные хвойные и вечнозеленые растения для живых изгородей и ландшафтных композиций.",
      "products": [
        {
          "id": "biryuchina-c2",
          "name": "Бирючина обыкновенная",
          "latinName": "Ligustrum vulgare",
          "description": "Бирючина обыкновенная — неприхотливый декоративный кустарник для живых изгородей и озеленения участков. Быстро растет, легко формируется и сохраняет аккуратную крону. Хорошо переносит стрижку, городские условия и перепады температур; нетребовательна к почвам, растет на солнце и в полутени.",
          "pricePrefix": "от",
          "price": 10,
          "currency": "руб",
          "size": "C2",
          "image": "assets/images/birucha.png",
          "heroImage": "assets/images/birucha.png",
          "link": "product.html?id=biryuchina-c2",
          "variants": [
            { "size": "1 л.", "price": 5 },
            { "size": "2 л.", "price": 10 },
            { "size": "5 л.", "price": 100 }
          ]
        },
        {
          "id": "thuja-occ-c2",
          "name": "Туя западная",
          "latinName": "Thuja occidentalis",
          "description": "Компактная хвойная для живых изгородей и солитеров.",
          "price": 18,
          "currency": "руб",
          "size": "C2",
          "image": "assets/images/birucha.png",
          "link": "product.html?id=thuja-occ-c2",
          "variants": [
            { "size": "C2", "price": 18 },
            { "size": "C5", "price": 32 }
          ]
        },
        {
          "id": "juniperus-blue",
          "name": "Можжевельник чешуйчатый",
          "latinName": "Juniperus squamata",
          "description": "Сизая хвоя, стелющаяся крона.",
          "price": 15,
          "currency": "руб",
          "size": "C3",
          "image": "assets/images/birucha.png",
          "link": "product.html?id=juniperus-blue",
          "variants": [
            { "size": "C3", "price": 15 },
            { "size": "C5", "price": 24 }
          ]
        },
        {
          "id": "picea-glauca",
          "name": "Ель канадская",
          "latinName": "Picea glauca",
          "description": "Карликовая форма, мягкая хвоя.",
          "price": 25,
          "currency": "руб",
          "size": "P9",
          "image": "assets/images/birucha.png",
          "link": "product.html?id=picea-glauca",
          "variants": [
            { "size": "P9", "price": 25 },
            { "size": "C5", "price": 48 }
          ]
        },
        {
          "id": "pinus-mugo",
          "name": "Сосна горная",
          "latinName": "Pinus mugo",
          "description": "Низкорослая, для альпинариев.",
          "price": 28,
          "currency": "руб",
          "size": "C5",
          "image": "assets/images/birucha.png",
          "link": "product.html?id=pinus-mugo",
          "variants": [
            { "size": "C5", "price": 28 },
            { "size": "C7.5", "price": 39 }
          ]
        },
        {
          "id": "picea-abies",
          "name": "Ель обыкновенная",
          "latinName": "Picea abies",
          "description": "Классическая лесная ель.",
          "price": 20,
          "currency": "руб",
          "size": "C5",
          "image": "assets/images/birucha.png",
          "link": "product.html?id=picea-abies",
          "variants": [
            { "size": "C5", "price": 20 },
            { "size": "C10", "price": 55 }
          ]
        },
        {
          "id": "thuja-smaragd",
          "name": "Туя Смарагд",
          "latinName": "Thuja occidentalis 'Smaragd'",
          "description": "Стройная колонна для изгородей.",
          "price": 22,
          "currency": "руб",
          "size": "C7.5",
          "image": "assets/images/birucha.png",
          "link": "product.html?id=thuja-smaragd",
          "variants": [
            { "size": "C7.5", "price": 22 },
            { "size": "C10", "price": 35 }
          ]
        },
        {
          "id": "taxus-baccata",
          "name": "Тис ягодный",
          "latinName": "Taxus baccata",
          "description": "Теневыносливый хвойник.",
          "price": 35,
          "currency": "руб",
          "size": "C10",
          "image": "assets/images/birucha.png",
          "link": "product.html?id=taxus-baccata",
          "variants": [
            { "size": "C10", "price": 35 },
            { "size": "C15", "price": 52 }
          ]
        },
        {
          "id": "chamaecyparis",
          "name": "Кипарисовик горохоплодный",
          "latinName": "Chamaecyparis pisifera",
          "description": "Ажурная хвоя, голубоватый оттенок.",
          "price": 16,
          "currency": "руб",
          "size": "C3",
          "image": "assets/images/birucha.png",
          "link": "product.html?id=chamaecyparis",
          "variants": [
            { "size": "C3", "price": 16 },
            { "size": "C5", "price": 23 }
          ]
        },
        {
          "id": "thuja-compacta",
          "name": "Туя Компакта",
          "latinName": "Thuja occidentalis 'Compacta'",
          "description": "Плотная крона, медленный рост.",
          "price": 14,
          "currency": "руб",
          "size": "C2",
          "image": "assets/images/birucha.png",
          "link": "product.html?id=thuja-compacta",
          "variants": [
            { "size": "C2", "price": 14 },
            { "size": "C5", "price": 26 }
          ]
        }
      ]
    },
    {
      "slug": "shrubs",
      "title": "Лиственные кустарники",
      "description": "Цветущие и декоративнолистные кустарники для садовых композиций.",
      "products": [
        {
          "id": "spiraea-japonica",
          "name": "Спирея японская",
          "latinName": "Spiraea japonica",
          "description": "Низкий кустарник с розовыми соцветиями.",
          "price": 9,
          "currency": "руб",
          "size": "C2",
          "image": "assets/images/birucha.png",
          "link": "product.html?id=spiraea-japonica",
          "variants": [
            { "size": "C2", "price": 9 },
            { "size": "C3", "price": 13 }
          ]
        },
        {
          "id": "physocarpus-diablo",
          "name": "Пузыреплодник Дьяболо",
          "latinName": "Physocarpus opulifolius 'Diabolo'",
          "description": "Бордовые листья, бело-розовые шары цветков.",
          "price": 13,
          "currency": "руб",
          "size": "C3",
          "image": "assets/images/birucha.png",
          "link": "product.html?id=physocarpus-diablo",
          "variants": [
            { "size": "C3", "price": 13 },
            { "size": "C5", "price": 21 }
          ]
        }
      ]
    }
  ]
}
